[
	{
		"inputs": [],
		"stateMutability": "nonpayable",
		"type": "constructor"
	},
	{
		"inputs": [
			{
				"internalType": "address",
				"name": "owner",
				"type": "address"
			}
		],
		"name": "OwnableInvalidOwner",
		"type": "error"
	},
	{
		"inputs": [
			{
				"internalType": "address",
				"name": "account",
				"type": "address"
			}
		],
		"name": "OwnableUnauthorizedAccount",
		"type": "error"
	},
	{
		"anonymous": false,
		"inputs": [
			{
				"indexed": true,
				"internalType": "uint256",
				"name": "itemId",
				"type": "uint256"
			},
			{
				"indexed": true,
				"internalType": "address",
				"name": "renter",
				"type": "address"
			},
			{
				"indexed": false,
				"internalType": "uint256",
				"name": "rentalFee",
				"type": "uint256"
			},
			{
				"indexed": false,
				"internalType": "uint256",
				"name": "collateral",
				"type": "uint256"
			},
			{
				"indexed": false,
				"internalType": "uint256",
				"name": "timestamp",
				"type": "uint256"
			}
		],
		"name": "DepositReceived",
		"type": "event"
	},
	{
		"anonymous": false,
		"inputs": [
			{
				"indexed": true,
				"internalType": "address",
				"name": "previousOwner",
				"type": "address"
			},
			{
				"indexed": true,
				"internalType": "address",
				"name": "newOwner",
				"type": "address"
			}
		],
		"name": "OwnershipTransferred",
		"type": "event"
	},
	{
		"anonymous": false,
		"inputs": [
			{
				"indexed": true,
				"internalType": "address",
				"name": "recipient",
				"type": "address"
			},
			{
				"indexed": false,
				"internalType": "uint256",
				"name": "amount",
				"type": "uint256"
			},
			{
				"indexed": true,
				"internalType": "uint256",
				"name": "itemId",
				"type": "uint256"
			},
			{
				"indexed": false,
				"internalType": "string",
				"name": "payoutType",
				"type": "string"
			},
			{
				"indexed": false,
				"internalType": "uint256",
				"name": "timestamp",
				"type": "uint256"
			}
		],
		"name": "PayoutProcessed",
		"type": "event"
	},
	{
		"inputs": [
			{
				"internalType": "uint256",
				"name": "itemId",
				"type": "uint256"
			},
			{
				"internalType": "uint256",
				"name": "rentalFee",
				"type": "uint256"
			},
			{
				"internalType": "uint256",
				"name": "collateral",
				"type": "uint256"
			}
		],
		"name": "deposit",
		"outputs": [],
		"stateMutability": "payable",
		"type": "function"
	},
	{
		"inputs": [],
		"name": "getContractBalance",
		"outputs": [
			{
				"internalType": "uint256",
				"name": "",
				"type": "uint256"
			}
		],
		"stateMutability": "view",
		"type": "function"
	},
	{
		"inputs": [],
		"name": "owner",
		"outputs": [
			{
				"internalType": "address",
				"name": "",
				"type": "address"
			}
		],
		"stateMutability": "view",
		"type": "function"
	},
	{
		"inputs": [
			{
				"internalType": "address payable",
				"name": "recipient",
				"type": "address"
			},
			{
				"internalType": "uint256",
				"name": "amount",
				"type": "uint256"
			},
			{
				"internalType": "uint256",
				"name": "itemId",
				"type": "uint256"
			},
			{
				"internalType": "string",
				"name": "payoutType",
				"type": "string"
			}
		],
		"name": "payout",
		"outputs": [],
		"stateMutability": "nonpayable",
		"type": "function"
	},
	{
		"inputs": [],
		"name": "renounceOwnership",
		"outputs": [],
		"stateMutability": "nonpayable",
		"type": "function"
	},
	{
		"inputs": [
			{
				"internalType": "address",
				"name": "newOwner",
				"type": "address"
			}
		],
		"name": "transferOwnership",
		"outputs": [],
		"stateMutability": "nonpayable",
		"type": "function"
	},
	{
		"stateMutability": "payable",
		"type": "receive"
	}
]